<?xml version="1.0" encoding="utf-8" standalone="yes"?>
<?xml-stylesheet type="text/xsl" href="../../modx.prosilver.en.xsl"?>
<!--For security purposes, please check: http://www.phpbb.com/mods/ for the latest version of this MOD. Although MODs are checked before being allowed in the MODs Database there is no guarantee that there are no security problems within the MOD. No support will be given for MODs not found within the MODs Database which can be found at http://www.phpbb.com/mods/-->
<mod xmlns:xsi="http://www.w3.org/2001/XMLSchema-instance" xmlns="http://www.phpbb.com/mods/xml/modx-1.2.2.xsd">
  <header>
    <license>http://www.gnu.org/licenses/gpl-2.0.html GNU General Public License v2</license>
    <title lang="en-gb">WP-UNITED WordPress - phpBB Integration Mod</title>
    <description lang="en-gb">Tightly integrates phpBB3 and WordPress.</description>
    <author-notes lang="en-gb">Make sure you follow the instructions in the DIY INSTRUCTIONS section, in order for this MOD to work properly!
Visit http://www.wp-united.com for more help or information.
</author-notes>
    <author-group>
      <author>
        <realname>John Wells</realname>
        <email>admin@wp-united.com</email>
        <username>Jhong</username>
        <homepage>www.wp-united.com</homepage>
        <contributions />
      </author>
    </author-group>
    <mod-version>0.8.0RC2</mod-version>
    <installation>
      <level>intermediate</level>
      <time>912</time>
      <target-version>3.0.4</target-version>
    </installation>
    <link-group>
	<link type="parent" href="../../install.xml" lang="en">Main install file</link>
	<link type="template" href="../../templates/subsilver2.xml" lang="en">subsilver2</link>
	<link type="language" href="../../languages/de.xml" lang="de">Deutsch</link>
	<link type="language" href="../../languages/es.xml" lang="es">Espanol</link>
	<link type="language" href="languages/it.xml" lang="it">Italiano</link>	
	<link type="contrib" href="../convert_from_phpbb2/convert_from_phpbb2.xml" lang="en">Convert from phpBB2</link>
	<link type="contrib" href="../upgrading_from_v0.5.5_or_later/upgrade.xml" lang="en">Upgrading from WP-United v0.5.5 or later</link>
  </link-group>
  </header>

  
  <action-group>
    <copy>
      <file from="/root/blog.php" to="/blog.php" />
      <file from="/root/adm/style/acp_wp_united.html" to="/adm/style/acp_wp_united.html" />
      <file from="/root/includes/hooks/hook_wp-united.php" to="/includes/hooks/hook_wp-united.php" />
      <file from="/root/includes/acp/acp_wp_united.php" to="/includes/acp/acp_wp_united.php" />
      <file from="/root/includes/acp/info/acp_wp_united.php" to="/includes/acp/info/acp_wp_united.php" />
      <file from="/root/language/en/mods/admin_wp-united.php" to="/language/en/mods/admin_wp-united.php" />
      <file from="/root/language/en/mods/permissions_wp-united.php" to="/language/en/mods/permissions_wp-united.php" />
      <file from="/root/language/en/mods/wp-united.php" to="/language/en/mods/wp-united.php" />
      <file from="/root/styles/prosilver/template/blog.html" to="/styles/prosilver/template/blog.html" />
      <file from="/root/styles/subsilver2/template/blog.html" to="/styles/subsilver2/template/blog.html" />
      <file from="/root/wp-united/" to="/wp-united/" />
    </copy>
    
    <open src="includes/functions.php">
      <edit>
        <find><![CDATA[	require_once($phpbb_root_path . 'wp-united/wpu-actions.' . $phpEx);
	$GLOBALS['wpu_actions']->do_tail();
	]]></find>
        <action type="replace-with"></action>
        <comment lang="en-gb">Delete the lines you added for a previous version of WP-United.</comment>
      </edit>
      <edit>
        <find><![CDATA[
	require_once($phpbb_root_path . 'wp-united/wpu-actions.' . $phpEx);
	$GLOBALS['wpu_actions']->do_head($template);
]]></find>
        <action type="replace-with"></action>
        <comment lang="en-gb">Delete the lines you added for a previous version of WP-United.</comment>
      </edit>      
    </open>
        
    <open src="language/en/common.php">
      <edit>
        <find><![CDATA[//WP-United
	'BLOG'			=> 	'WordPress Blog',
	'VISIT_BLOG'		=>	'Visit User\'s Blog',
	'ACP_WP_UNITED' 	=> 	'WP-United',
	'ACP_WPU_MAINPAGE'	=>	'WP-United Administration',
	'ACP_WPU_CATMAIN'	=> 	'WP-United Admin',
	'ACP_WPU_CATSETUP'	=>	'Set Up WP-United',
	'ACP_WPU_CATMANAGE'	=>	'Manage User Integration',
	'ACP_WPU_CATSUPPORT'	=>	'Support WP-United',
	'ACP_WPU_CATOTHER'	=>	'Other',
	'ACP_WPU_MAINTITLE'	=>	'Main Page',
	'ACP_WPU_DETAILED'	=>	'All Settings On A Page',
	'ACP_WPU_WIZARD'	=> 	'Setup Wizard',
	'ACP_WPU_USERMAP'	=> 	'User Integration Mapping Tool',
	'ACP_WPU_PERMISSIONS'	=> 	'Administer permissions',		
	'ACP_WPU_DONATE'	=> 	'Donate to WP-United',
	'ACP_WPU_UNINSTALL'	=> 	'Uninstall WP-United',
	'ACP_WPU_RESET'		=> 	'Reset WP-United',]]>
		</find>
      </edit>
      <action type="replace-with"></action>
        <comment lang="en-gb">Delete any lines you added for a previous version of WP-United.</comment>
		   
    </open>

     <diy-instructions lang="en-gb"><![CDATA[	

THEME CHANGES
-------------
If you need to install the template modifications for the subSilver2 template, use the subsilver2.xml file in the templates folder.

if you are using another theme based on prosilver, make the above prosilver changes to your theme now.

Remember to purge the phpBB template cache, and refresh your themes after making these changes.

IMPORTANT NEXT STEPS
--------------------

After making all the edits, you must complete the following steps:

1. Run the wpu-install.php script that you copied to your phpBB root folder, by accessing http://your-site-toot/wpu-install.php. When done, delete wpu-install.php.

2. Make sure you have installed WordPress. If you need help, look at the instructions on the WordPress Codex, here: http://codex.wordpress.org/Installing_WordPress

3. IMPORTANT: Copy the file wpu-plugin.php from your phpbb-root/wp-united folder to your WordPress plugins folder (wp-includes/plugins). (This was not required in older versions of WP-United)

4. Run the Setup Wizard, under the WP-United tab that will appear in your ACP.

For more detailed instructions, please visit http://www.wp-united.com

REPORTING BUGS / GETTING HELP
-----------------------------

Please remember, 95% of reported bugs are user error. If you encounter any problems, re-read the above steps carefully, and make sure you have done everything as instructed, and try installing the mod using AutoMod. 

Check that your phpBB server settings (especially "script path") and WordPress settings are correct, then try re-running the WP-United install wizard (WP-United tab in the phpBB Admin Control Panel).

If it still fails, please:
(1) If you are getting blank pages, turn on PHP error reporting or look in your server log to find the underlying cause of the problem. We can't respond to any support requests referring to "blank pages" without accompanying error output.
(2) Use "Debug Info To Post" function, located under the WP-United Admin Control Panel tab, to getrelevant debug information.

Post this information, together with full details of any error, and what you did to generate the error, on http://www.wp-united.com , after performing a search for similar issues.

]]></diy-instructions>
  </action-group>
</mod>
